inventree_dymo/InvenTreeDymo550Plugin.py
inventree_dymo/__init__.py
inventree_dymo/conn.py
inventree_dymo/status.py
inventree_dymo/test_conn.py
inventree_dymo/test_status.py
inventree_dymo/version.py
inventree_dymo_550_plugin-0.1.1.dist-info/licenses/LICENSE
inventree_dymo_550_plugin-0.1.1.dist-info/METADATA
inventree_dymo_550_plugin-0.1.1.dist-info/WHEEL
inventree_dymo_550_plugin-0.1.1.dist-info/entry_points.txt
inventree_dymo_550_plugin-0.1.1.dist-info/top_level.txt
inventree_dymo_550_plugin-0.1.1.dist-info/RECORD
