Metadata-Version: 2.4
Name: inventree-dymo-550-plugin
Version: 0.1.1
Summary: Dymo 550 Label printer driver plugin for InvenTree
Home-page: https://github.com/bobvawter/inventree-dymo-550-driver
Author: bobvawter
Author-email: bob@vawter.org
License: MIT
Keywords: inventree dymo
Requires-Python: >=3.9
License-File: LICENSE
Dynamic: author
Dynamic: author-email
Dynamic: description
Dynamic: description-content-type
Dynamic: home-page
Dynamic: keywords
Dynamic: license
Dynamic: license-file
Dynamic: requires-python
Dynamic: summary
